proof_of_training/__init__.py
proof_of_training/abi.json
proof_of_training/model_metadata.py
proof_of_training/proof_of_training.py
proof_of_training-0.7.0.dist-info/METADATA
proof_of_training-0.7.0.dist-info/WHEEL
proof_of_training-0.7.0.dist-info/RECORD
