Metadata-Version: 2.1
Name: proof-of-training
Version: 0.7.0
Summary: Proof of Training SDK for submitting and verifying model training metadata on blockchain.
Author: Thomas
Author-email: wxy_000000@qq.com
Requires-Python: >=3.11,<4.0
Classifier: Programming Language :: Python :: 3
Classifier: Programming Language :: Python :: 3.11
Classifier: Programming Language :: Python :: 3.12
Classifier: Programming Language :: Python :: 3.13
Requires-Dist: protobuf (<4.0.0)
Requires-Dist: pymerkle (>=6.1.0,<7.0.0)
Requires-Dist: pytest (>=8.2.1,<9.0.0)
Requires-Dist: web3 (>=7.4.0,<8.0.0)
